Workbook

Sheet Menu Flow
A2: Carbon Passport demo walkthrough
A3: Synthetic PoC data only. Update yellow cells. Calculated outputs use formulas.
A5: Step | B5: Menu | C5: Action | D5: What to enter or provide | E5: What you get | F5: Workbook reference | G5: Your progress
A6: 1 | B6: Organisation | C6: Register company and facility | D6: Use Company Setup. Add assets and processes. | E6: Organisation, facility and product IDs. | F6: Company Setup | G6: Not started
A7: 2 | B7: Value Chain | C7: Add suppliers and receipts | D7: Create two suppliers and receive material lots. | E7: Traceable materials and stock balances. | F7: Materials and Batch | G7: Not started
A8: 3 | B8: Data | C8: Create batch and activities | D8: Record consumption, output, electricity, diesel and freight. | E8: Validated batch activities and evidence references. | F8: Materials and Batch | G8: Not started
A9: 4 | B9: Administration | C9: Load demo factors | D9: Use factors labelled Synthetic PoC factor, version DEMO-EF-v1. | E9: Factors available for calculation. | F9: Emissions | G9: Not started
A10: 5 | B10: Carbon Accounting | C10: Calculate period emissions | D10: October 2026; this one batch contains all demo period activity. | E10: Scope totals and inventory. | F10: Emissions | G10: Not started
A11: 6 | B11: PCF | C11: Calculate batch footprint | D11: Cradle to plant gate; assign all listed activities to the batch; no scrap credit. | E11: 1,222 kgCO2e total and 1.222 kgCO2e/kg at seed inputs. | F11: Emissions | G11: Not started
A12: 7 | B12: CBAM | C12: Assess applicability | D12: India to Germany; classification pending. Do not copy PCF into CBAM. | E12: Needs classification assessment. | F12: Review and Shipment | G12: Not started
A13: 8 | B13: MRV and Verification | C13: Submit and review | D13: Operator submits evidence; Demo Verifier reviews exact calculation version. | E13: Approved demo snapshot or changes requested. | F13: Review and Shipment | G13: Not started
A14: 9 | B14: Carbon Passports | C14: Issue and verify | D14: Readiness, Preview, Sign and Issue, Registry, Detail, QR, Versions. | E14: DEMO-CP-001 after approval; public verification page. | F14: Review and Shipment | G14: Not started
A15: 10 | B15: Value Chain | C15: Record shipment | D15: Link batch and passport; enter shipped mass and freight activity. | E15: Shipment record and separate delivery extension. | F15: Review and Shipment | G15: Not started
A16: 11 | B16: Analytics | C16: Inspect contributions | D16: Compare electricity, inputs, diesel and freight. | E16: Emissions hotspots and manufacturing intensity. | F16: Emissions | G16: Not started
... A19: 14 | B19: Home | C19: Confirm completion | D19: Review current records and missing actions. | E19: One organisation, plant, batch and approved passport after completing actions. | F19: All sheets | G19: Not started

Sheet Company Setup
A2: Dummy company facility and product
A3: Synthetic PoC data only. Update yellow cells. Calculated outputs use formulas.
A5: Record | B5: Field | C5: Value
A6: Company | B6: Company name | C6: GreenBridge Manufacturing Pvt Ltd
A7: Company | B7: Company code | C7: DEMO-ORG-001
A8: Company | B8: Country | C8: India
A9: Company | B9: Industry | C9: General Manufacturing
A10: Company | B10: Address | C10: Demo Industrial Estate, Hyderabad, Telangana
A11: Company | B11: Registration | C11: DEMO-REG-001
A12: Company | B12: Tax identifier | C12: Leave blank or use supported demo placeholder
A13: Company | B13: Contact | C13: Demo Company Administrator
A14: Company | B14: Email | C14: admin@example.com
A15: Company | B15: Reporting year | C15: 2026
A16: Company | B16: Currency | C16: INR
A17: Company | B17: Export market | C17: Germany, European Union
A18: Facility | B18: Facility name | C18: GreenBridge Hyderabad Plant
A19: Facility | B19: Facility code | C19: DEMO-FAC-001
A20: Facility | B20: Location | C20: Hyderabad, India
A21: Facility | B21: Timezone | C21: Asia/Kolkata
A22: Facility | B22: Processes | C22: Material preparation; manufacturing; finishing; packaging
A23: Facility | B23: Assets | C23: Production Line 01; Main Electricity Meter; Diesel Generator
A24: Product | B24: Product name | C24: Manufactured Component A
A25: Product | B25: Product code | C25: DEMO-PROD-001
A26: Product | B26: Category | C26: General manufactured goods
A27: Product | B27: Unit | C27: kg
... A30: Product | B30: Boundary | C30: Cradle to plant gate

Sheet Sheet2

Sheet Materials and Batch
A2: Procurement and production records
A3: Synthetic PoC data only. Update yellow cells. Calculated outputs use formulas.
A5: Record | B5: Field or supplier | C5: ID or value | D5: Quantity | E5: Unit | F5: Purpose or evidence
A6: Material | B6: Demo Materials Supplier | C6: LOT-MAT-001 | D6: 1200 | E6: kg | F6: Input Material A received; India; DEMO-INV-001
A7: Material | B7: Demo Packaging Supplier | C7: LOT-PACK-001 | D7: 50 | E7: kg | F7: Packaging received; India; DEMO-INV-002
A8: Consumption | B8: Input Material A | C8: LOT-MAT-001 | D8: 1100 | E8: kg | F8: Assigned to DEMO-BATCH-001
A9: Consumption | B9: Packaging | C9: LOT-PACK-001 | D9: 50 | E9: kg | F9: Assigned to DEMO-BATCH-001
A10: Stock | B10: Input Material A balance | C10: LOT-MAT-001 | D10: =D6-D8 -> 100 | E10: kg | F10: Received less consumed
A11: Stock | B11: Packaging balance | C11: LOT-PACK-001 | D11: =D7-D9 -> 0 | E11: kg | F11: Received less consumed
A12: Batch | B12: Batch code | C12: DEMO-BATCH-001 | F12: Product DEMO-PROD-001; facility DEMO-FAC-001
A13: Batch | B13: Production date | C13: 46301 | F13: 09:00 to 17:00 Asia/Kolkata
A14: Production | B14: Finished output | C14: DEMO-BATCH-001 | D14: 1000 | E14: kg | F14: Output excludes packaging mass
A15: Production | B15: Manufacturing scrap | C15: DEMO-BATCH-001 | D15: 100 | E15: kg | F15: No emissions credit; record disposition
A16: Activity | B16: Electricity | C16: DEMO-ACT-001 | D16: 1000 | E16: kWh | F16: Manual demo meter evidence
A17: Activity | B17: Diesel | C17: DEMO-ACT-002 | D17: 20 | E17: L | F17: Manual demo fuel evidence
A18: Activity | B18: Inbound freight | C18: DEMO-ACT-003 | D18: 220 | E18: tonne-km | F18: Manual demo transport evidence
A19: Activity | B19: Outbound freight | C19: DEMO-ACT-004 | D19: 500 | E19: tonne-km | F19: Shipment extension only
A20: Shipment | B20: Shipped quantity | C20: DEMO-SHIP-001 | D20: 1000 | E20: kg | F20: Demo European Buyer; Germany

Sheet Emissions
A2: Demo factors and calculated footprints
A3: Synthetic PoC data only. Update yellow cells. Calculated outputs use formulas.
A5: Activity | B5: Scope or boundary | C5: Quantity | D5: Activity unit | E5: Demo factor | F5: Factor unit | G5: Emissions kgCO2e
A6: Diesel | B6: Scope 1 | C6: ='Materials and Batch'!D17 -> 20 | D6: L | E6: 2.5 | F6: kgCO2e/L | G6: =IF(OR(C6="",E6=""),"Missing input",C6*E6) -> 50
A7: Electricity | B7: Scope 2 | C7: ='Materials and Batch'!D16 -> 1000 | D7: kWh | E7: 0.7 | F7: kgCO2e/kWh | G7: =IF(OR(C7="",E7=""),"Missing input",C7*E7) -> 700
A8: Input Material A | B8: Scope 3 | C8: ='Materials and Batch'!D8 -> 1100 | D8: kg | E8: 0.4 | F8: kgCO2e/kg | G8: =IF(OR(C8="",E8=""),"Missing input",C8*E8) -> 440
A9: Packaging | B9: Scope 3 | C9: ='Materials and Batch'!D9 -> 50 | D9: kg | E9: 0.2 | F9: kgCO2e/kg | G9: =IF(OR(C9="",E9=""),"Missing input",C9*E9) -> 10
A10: Inbound freight | B10: Scope 3 | C10: ='Materials and Batch'!D18 -> 220 | D10: tonne-km | E10: 0.1 | F10: kgCO2e/tonne-km | G10: =IF(OR(C10="",E10=""),"Missing input",C10*E10) -> 22
A11: Outbound freight | B11: Delivery extension | C11: ='Materials and Batch'!D19 -> 500 | D11: tonne-km | E11: 0.1 | F11: kgCO2e/tonne-km | G11: =IF(OR(C11="",E11=""),"Missing input",C11*E11) -> 50
A14: Metric | B14: Calculated result
A15: Manufacturing total kgCO2e | B15: =IF(COUNT(G6:G10)=5,SUM(G6:G10),"Missing input") -> 1222
A16: Finished output kg | B16: ='Materials and Batch'!D14 -> 1000
A17: Manufacturing kgCO2e/kg | B17: =IF(AND(ISNUMBER(B15),ISNUMBER(B16),B16>0),B15/B16,"Missing or invalid output") -> 1.222
A18: Outbound logistics kgCO2e | B18: =G11 -> 50
A19: Delivery total kgCO2e | B19: =IF(AND(ISNUMBER(B15),ISNUMBER(B18)),B15+B18,"Missing input") -> 1272
A20: Delivery kgCO2e/kg | B20: =IF(AND(ISNUMBER(B19),ISNUMBER(B16),B16>0),B19/B16,"Missing or invalid output") -> 1.272
A21: Scope 3 upstream kgCO2e | B21: =IF(COUNT(G8:G10)=3,SUM(G8:G10),"Missing input") -> 472
A24: Factor source: Synthetic PoC factor. Version DEMO-EF-v1. No real reporting use.
A25: Manufacturing boundary: cradle to plant gate. All activities allocated to this batch. No scrap credit.

Sheet Review and Shipment
A2: Review passport shipment and targets
A3: Synthetic PoC data only. Update yellow cells. Calculated outputs use formulas.
A5: Area | B5: Field or action | C5: Dummy entry or instruction | D5: Expected result
A6: CBAM | B6: Origin and destination | C6: India; Germany | D6: Needs classification assessment
A7: CBAM | B7: Classification | C7: Pending assessment | D7: Do not produce embedded emissions until classified and rules configured
A8: MRV | B8: Calculation version | C8: DEMO-PCF-v1 | D8: Submit activity evidence, receipts, factors and assumptions
A9: MRV | B9: Reviewer role | C9: Demo Verifier | D9: Operator cannot approve their calculation
A10: MRV | B10: Decision comment | C10: Reviewed for PoC workflow testing using synthetic activity data and factors. | D10: Demo verified after actual review action
A11: Passport | B11: Passport ID | C11: DEMO-CP-001 | D11: Issue only after readiness and approval
A12: Passport | B12: Product and batch | C12: DEMO-PROD-001; DEMO-BATCH-001 | D12: Links to approved calculation
A13: Passport | B13: Manufacturing PCF | C13: =Emissions!B17 -> 1.222 | D13: kgCO2e/kg; cradle to plant gate
A14: Passport | B14: Public QR | C14: Generate actual /verify/{token} URL in application | D14: Show current status without private evidence
A15: Passport | B15: Inner pages | C15: Readiness; Preview; Sign and Issue; Registry; Detail; QR; Versions | D15: Version history and validity remain visible
A16: Shipment | B16: Shipment ID | C16: DEMO-SHIP-001 | D16: Link batch and issued passport
A17: Shipment | B17: Buyer and destination | C17: Demo European Buyer; Germany | D17: Customer export package
A18: Shipment | B18: Quantity | C18: ='Materials and Batch'!D20 -> 1000 | D18: kg; do not exceed available output
A19: Shipment | B19: Delivery intensity | C19: =Emissions!B20 -> 1.272 | D19: kgCO2e/kg; separate extended boundary
A20: Policy | B20: Applicability | C20: Generic manufactured goods; classification pending | D20: Unresolved requirements remain visible
A21: Paris Alignment | B21: Baseline year | C21: 2026 | D21: Use selected baseline boundary
A22: Paris Alignment | B22: Baseline intensity | C22: =Emissions!B17 -> 1.222 | D22: kgCO2e/kg
A23: Paris Alignment | B23: Target year | C23: 2030 | D23: Illustrative target
A24: Paris Alignment | B24: Target intensity | C24: 1 | D24: kgCO2e/kg; self-reported demo target
A25: Paris Alignment | B25: Action | C25: Reduce electricity consumption | D25: Record project progress and evidence
A26: Home | B26: Completion expectation | C26: One company, plant, batch, approved calculation, passport and shipment | D26: Only show completed statuses after corresponding actions
A27: Evidence | B27: Upload instruction | C27: Use files labelled Synthetic invoice or reading for demo only | D27: This workbook does not perform application verification or issuance
